{
  "annotations": {
    "changelogDate": "20240313084736"
  },
  "applications": ["containerGoServer"],
  "dto": "mapstruct",
  "entityTableName": "carrier_account",
  "fields": [
    {
      "fieldName": "id",
      "fieldType": "Long"
    },
    {
      "fieldName": "name",
      "fieldType": "String",
      "fieldValidateRules": ["required"]
    },
    {
      "fieldName": "phone",
      "fieldType": "String",
      "fieldValidateRules": ["required"]
    },
    {
      "fieldName": "email",
      "fieldType": "String"
    },
    {
      "fieldName": "address",
      "fieldType": "String"
    }
  ],
  "jpaMetamodelFiltering": false,
  "name": "CarrierAccount",
  "pagination": "pagination",
  "relationships": [
    {
      "otherEntityName": "carrier",
      "relationshipName": "carrier",
      "relationshipSide": "left",
      "relationshipType": "many-to-one",
      "relationshipValidateRules": "required"
    }
  ],
  "searchEngine": "no",
  "service": "serviceImpl"
}
